device_ops/__init__.py
device_ops/cli.py
device_ops-0.1.2.dist-info/METADATA
device_ops-0.1.2.dist-info/WHEEL
device_ops-0.1.2.dist-info/entry_points.txt
device_ops-0.1.2.dist-info/RECORD
