Metadata-Version: 2.1
Name: device-ops
Version: 0.1.2
Summary: Admin tool for device operations over MQTT.
Author: surdouski
Author-email: michael.surdouski@gmail.com
Requires-Python: >=3.10,<4.0
Classifier: Programming Language :: Python :: 3
Classifier: Programming Language :: Python :: 3.10
Classifier: Programming Language :: Python :: 3.11
Classifier: Programming Language :: Python :: 3.12
Requires-Dist: click (>=8.1.7,<9.0.0)
Requires-Dist: daemonize (>=2.5.0,<3.0.0)
Requires-Dist: python-dotenv (>=1.0.1,<2.0.0)
Requires-Dist: rich (>=13.8.0,<14.0.0)
Requires-Dist: sniffs (==0.6.2)
